[{"ann_id":"7","ann_title":"","ann_content":"assets\/announcement\/guidelines.png","ann_status":"Approved","ann_receiver":"All","ann_approvedby":"045-2014-008","ann_timestatmp":"2025-04-23 16:22:33","ann_pinned":1,"ann_reported_by":null,"ann_report_reason":null,"bi_empno":"045-2014-008","bi_emplname":"Bongcawel","bi_empfname":"Meljoy","port_id":"7"},{"ann_id":"13","ann_title":"Star Awards Night 2025 Awardees! ?","ann_content":"assets\/announcement\/fb9e785c-5906-4473-b1a4-c7ad6bab4384.jfif,assets\/announcement\/de1f1e41-4ad1-42ef-aad7-ba3f97ec520b.jfif,assets\/announcement\/02bdf5c1-ca09-437e-96c1-54ae0b27db3e.jfif,assets\/announcement\/7100f713-4fb2-4205-8a12-77f119eb7062.jfif","ann_status":"Approved","ann_receiver":"All","ann_approvedby":"ZAM-2023-003","ann_timestatmp":"2025-04-29 16:00:11","ann_pinned":0,"ann_reported_by":null,"ann_report_reason":null,"bi_empno":"ZAM-2023-003","bi_emplname":"Magallon","bi_empfname":"Sheila Mae","port_id":"13"}]